files_by_date
test
