Metadata-Version: 1.1
Name: files-by-date
Version: 0.0.21
Summary: Moves files from one directory into another grouping by created month
Home-page: https://github.com/DEV3L/python-files-by-date
Author: Justin Beall
Author-email: jus.beall@gmail.com
License: UNKNOWN
Download-URL: https://github.com/DEV3L/python-files-by-date/tarball/0.0.21
Keywords: dev3l,file management
Platform: UNKNOWN
Classifier: Environment :: Console
Classifier: Intended Audience :: Developers
Classifier: License :: OSI Approved :: MIT License
Classifier: Operating System :: OS Independent
Classifier: Programming Language :: Python
Classifier: Programming Language :: Python :: 2.6
Classifier: Programming Language :: Python :: 2.7
Classifier: Programming Language :: Python :: 3
Classifier: Programming Language :: Python :: 3.3
Classifier: Programming Language :: Python :: 3.4
Classifier: Programming Language :: Python :: 3.5
Classifier: Topic :: Software Development :: Libraries :: Python Modules
